basehangul
