Metadata-Version: 1.0
Name: basehangul
Version: 1.1
Summary: Human-readable binary encoding, BaseHangul for Python
Home-page: https://github.com/ssut/basehangul
Author: SuHun Han
Author-email: ssut@ssut.me
License: UNKNOWN
Platform: UNKNOWN
